mllaunchpad/__init__.py
mllaunchpad/__main__.py
mllaunchpad/api.py
mllaunchpad/cli.py
mllaunchpad/config.py
mllaunchpad/datasources.py
mllaunchpad/logutil.py
mllaunchpad/model_actions.py
mllaunchpad/model_interface.py
mllaunchpad/resource.py
mllaunchpad/wsgi.py
mllaunchpad/yaml_loader.py
tests/__init__.py
tests/mock_model.py
tests/mock_plugin.py
tests/test_api.py
tests/test_cli.py
tests/test_config.py
tests/test_datasources.py
tests/test_examples.py
tests/test_logutil.py
tests/test_model_actions.py
tests/test_resource.py
tests/test_wsgi.py
tests/test_yaml_loader.py
mllaunchpad-1.1.0.dist-info/LICENSE
mllaunchpad-1.1.0.dist-info/METADATA
mllaunchpad-1.1.0.dist-info/WHEEL
mllaunchpad-1.1.0.dist-info/entry_points.txt
mllaunchpad-1.1.0.dist-info/top_level.txt
mllaunchpad-1.1.0.dist-info/zip-safe
mllaunchpad-1.1.0.dist-info/RECORD
