Metadata-Version: 2.1
Name: mllaunchpad
Version: 1.1.0
Summary: Deploy Machine Learning Solutions with Ease
Home-page: https://github.com/schuderer/mllaunchpad/
Author: Andreas Schuderer
Author-email: pypi@schuderer.net
License: Apache License, Version 2.0
Project-URL: Documentation, https://mllaunchpad.readthedocs.io/
Project-URL: Changelog, https://mllaunchpad.readthedocs.io/en/latest/changelog.html
Project-URL: Source, https://github.com/schuderer/mllaunchpad
Project-URL: Issues, https://github.com/schuderer/mllaunchpad/issues
Keywords: mllaunchpad,abstraction layer,publishing,deployment,machine learning,lifecycle
Platform: UNKNOWN
Classifier: Development Status :: 5 - Production/Stable
Classifier: Operating System :: OS Independent
Classifier: Intended Audience :: Developers
Classifier: Intended Audience :: Science/Research
Classifier: License :: OSI Approved :: Apache Software License
Classifier: Natural Language :: English
Classifier: Programming Language :: Python :: 3
Classifier: Programming Language :: Python :: 3.6
Classifier: Programming Language :: Python :: 3.7
Classifier: Programming Language :: Python :: 3.8
Requires-Python: >=3.6
License-File: LICENSE
Requires-Dist: flask
Requires-Dist: flask-restful
Requires-Dist: werkzeug
Requires-Dist: ramlfications
Requires-Dist: dill
Requires-Dist: pandas
Requires-Dist: numpy
Requires-Dist: pyyaml
Requires-Dist: Click
Provides-Extra: dev
Requires-Dist: nox ; extra == 'dev'
Requires-Dist: Sphinx (==2.4.3) ; extra == 'dev'
Requires-Dist: sphinx-autobuild (==0.7.1) ; extra == 'dev'
Requires-Dist: sphinx-click (==2.3.1) ; extra == 'dev'
Requires-Dist: sphinxcontrib-apidoc (==0.3.0) ; extra == 'dev'
Requires-Dist: docutils (==0.17.1) ; extra == 'dev'
Requires-Dist: seed-isort-config ; extra == 'dev'
Requires-Dist: isort ; extra == 'dev'
Requires-Dist: black ; extra == 'dev'
Requires-Dist: mypy ; extra == 'dev'
Requires-Dist: flake8 ; extra == 'dev'
Requires-Dist: flake8-isort ; extra == 'dev'
Requires-Dist: bandit ; extra == 'dev'
Requires-Dist: twine ; extra == 'dev'
Requires-Dist: wheel ; extra == 'dev'
Requires-Dist: pytest (==5.3.5) ; extra == 'dev'
Requires-Dist: pytest-runner (==5.2) ; extra == 'dev'
Requires-Dist: pytest-cov (==2.8.1) ; extra == 'dev'
Requires-Dist: coverage (==5.0.3) ; extra == 'dev'
Requires-Dist: ipykernel ; (sys_platform == "darwin") and extra == 'dev'
Requires-Dist: python-language-server[all] ; (sys_platform == "darwin") and extra == 'dev'
Provides-Extra: docs
Requires-Dist: Sphinx (==2.4.3) ; extra == 'docs'
Requires-Dist: sphinx-autobuild (==0.7.1) ; extra == 'docs'
Requires-Dist: sphinx-click (==2.3.1) ; extra == 'docs'
Requires-Dist: sphinxcontrib-apidoc (==0.3.0) ; extra == 'docs'
Requires-Dist: docutils (==0.17.1) ; extra == 'docs'
Provides-Extra: examples
Requires-Dist: cx-oracle ; extra == 'examples'
Requires-Dist: scikit-learn ; extra == 'examples'
Requires-Dist: keras ; extra == 'examples'
Requires-Dist: tensorflow ; extra == 'examples'
Requires-Dist: gunicorn ; (sys_platform == "darwin") and extra == 'examples'
Provides-Extra: lint
Requires-Dist: seed-isort-config ; extra == 'lint'
Requires-Dist: isort ; extra == 'lint'
Requires-Dist: black ; extra == 'lint'
Requires-Dist: mypy ; extra == 'lint'
Requires-Dist: flake8 ; extra == 'lint'
Requires-Dist: flake8-isort ; extra == 'lint'
Requires-Dist: bandit ; extra == 'lint'
Provides-Extra: release
Requires-Dist: twine ; extra == 'release'
Requires-Dist: wheel ; extra == 'release'
Provides-Extra: test
Requires-Dist: pytest (==5.3.5) ; extra == 'test'
Requires-Dist: pytest-runner (==5.2) ; extra == 'test'
Requires-Dist: pytest-cov (==2.8.1) ; extra == 'test'
Requires-Dist: coverage (==5.0.3) ; extra == 'test'
